subextract/__init__.py
subextract/cli.py
subextract/language.py
subextract-0.2.1.dist-info/entry_points.txt
subextract-0.2.1.dist-info/WHEEL
subextract-0.2.1.dist-info/METADATA
subextract-0.2.1.dist-info/RECORD
